Metadata-Version: 1.1
Name: NHANES-semantic-data-dictionary-annotation
Version: 0.1
Summary: Scripts for extracting semantic data dictionaries from NHANES data
Home-page: https://github.com/rashidsabbir/extractor
Author: Ryan Sherman, Sabbir Rashid
Author-email: rjsfox8@gmail.com
License: MIT
Platform: UNKNOWN
Classifier: Development Status :: 3 - Alpha
Classifier: Intended Audience :: Developers
